torchy/__init__.py
torchy/nn/__init__.py
torchy/nn/basetorch.py
torchy/utils/data/__init__.py
torchy/utils/data/new_utils.py
torchy-0.1.3.dist-info/METADATA
torchy-0.1.3.dist-info/WHEEL
torchy-0.1.3.dist-info/licenses/LICENSE.txt
torchy-0.1.3.dist-info/RECORD
