Metadata-Version: 2.1
Name: torchy
Version: 0.1.3
Summary: A pytorch wrapper that makes .fit() (and others) possible in nn.Module!
Project-URL: documentation, https://github.com/ashimdahal/torchy/blob/master/docs/README.md
Project-URL: repository, https://github.com/ashimdahal/torchy.git
Project-URL: Bugs, https://github.com/ashimdahal/torchy/issues
Author: Ashim Dahal
Author-email: codeashim@gmail.com
License: MIT License
License-File: LICENSE.txt
Keywords: Deep Learning,PyTorch,Tensorflow,Torch
Classifier: Development Status :: 4 - Beta
Classifier: Intended Audience :: Developers
Classifier: Operating System :: OS Independent
Classifier: Programming Language :: Python :: 3.7
Classifier: Topic :: Scientific/Engineering :: Artificial Intelligence
Requires-Python: >=3.6
Requires-Dist: torch>=1.12.1
Requires-Dist: tqdm
